ghga_connector/__init__.py
ghga_connector/__main__.py
ghga_connector/cli.py
ghga_connector/config.py
ghga_connector/constants.py
ghga_connector/core/__init__.py
ghga_connector/core/client.py
ghga_connector/core/exceptions.py
ghga_connector/core/file_operations.py
ghga_connector/core/http_translation.py
ghga_connector/core/main.py
ghga_connector/core/message_display.py
ghga_connector/core/structs.py
ghga_connector/core/work_package.py
ghga_connector/core/api_calls/__init__.py
ghga_connector/core/api_calls/utils.py
ghga_connector/core/api_calls/well_knowns.py
ghga_connector/core/crypt/__init__.py
ghga_connector/core/crypt/abstract_bases.py
ghga_connector/core/crypt/checksums.py
ghga_connector/core/crypt/decryption.py
ghga_connector/core/crypt/encryption.py
ghga_connector/core/downloading/__init__.py
ghga_connector/core/downloading/abstract_downloader.py
ghga_connector/core/downloading/api_calls.py
ghga_connector/core/downloading/batch_processing.py
ghga_connector/core/downloading/downloader.py
ghga_connector/core/downloading/progress_bar.py
ghga_connector/core/downloading/structs.py
ghga_connector/core/uploading/__init__.py
ghga_connector/core/uploading/abstract_uploader.py
ghga_connector/core/uploading/main.py
ghga_connector/core/uploading/structs.py
ghga_connector/core/uploading/uploader.py
ghga_connector-1.8.0.dist-info/licenses/LICENSE
ghga_connector-1.8.0.dist-info/METADATA
ghga_connector-1.8.0.dist-info/WHEEL
ghga_connector-1.8.0.dist-info/entry_points.txt
ghga_connector-1.8.0.dist-info/top_level.txt
ghga_connector-1.8.0.dist-info/RECORD
