Metadata-Version: 2.4
Name: ghga_connector
Version: 1.8.0
Summary: GHGA Connector - A CLI client application for interacting with the GHGA system.
Author-email: "German Human Genome Phenome Archive (GHGA)" <contact@ghga.de>
License: Apache 2.0
Project-URL: Repository, https://github.com/ghga-de/ghga-connector
Classifier: Development Status :: 5 - Production/Stable
Classifier: Operating System :: POSIX :: Linux
Classifier: Programming Language :: Python :: 3
Classifier: Programming Language :: Python :: 3.12
Classifier: License :: OSI Approved :: Apache Software License
Classifier: Topic :: Internet :: WWW/HTTP :: HTTP Servers
Classifier: Topic :: Software Development :: Libraries
Classifier: Intended Audience :: Developers
Requires-Python: >=3.10
License-File: LICENSE
Requires-Dist: typer~=0.15
Requires-Dist: crypt4gh<2,>=1.6
Requires-Dist: ghga-service-commons[crypt]>=4.1.0
Requires-Dist: hexkit[s3]>=5.1
Requires-Dist: rich<15,>=14.0
Requires-Dist: tenacity<10,>=9.0.0
Requires-Dist: hishel<0.2,>=0.1.1
Dynamic: license-file
